findsrc.py
findsrc-1.1.5.dist-info/LICENSE
findsrc-1.1.5.dist-info/METADATA
findsrc-1.1.5.dist-info/WHEEL
findsrc-1.1.5.dist-info/entry_points.txt
findsrc-1.1.5.dist-info/top_level.txt
findsrc-1.1.5.dist-info/RECORD
