Metadata-Version: 2.1
Name: findsrc
Version: 1.1.5
Summary: Search tool for sources
Home-page: https://github.com/timxx/findsrc
Author: Weitian Leung
Author-email: weitianleung@gmail.com
License: Apache-2.0
Keywords: find tool source grep
Platform: Platform Independent
Classifier: Intended Audience :: Developers
Classifier: License :: OSI Approved :: Apache Software License
Classifier: Operating System :: OS Independent
Classifier: Programming Language :: Python :: 3
Classifier: Topic :: Utilities
Requires-Python: >=3.5
License-File: LICENSE
Requires-Dist: colorama ; platform_system == "Windows"
